bldg_point_clustering/__init__.py
bldg_point_clustering/heuristics.yml
bldg_point_clustering/cluster/__init__.py
bldg_point_clustering/cluster/cluster.py
bldg_point_clustering/featurizer/__init__.py
bldg_point_clustering/featurizer/featurizer.py
bldg_point_clustering/helper/__init__.py
bldg_point_clustering/helper/helper.py
bldg_point_clustering/metrics/__init__.py
bldg_point_clustering/metrics/metrics.py
bldg_point_clustering/plotter/__init__.py
bldg_point_clustering/plotter/plotter.py
bldg_point_clustering/tokenizer/__init__.py
bldg_point_clustering/tokenizer/tokenizers.py
bldg_point_clustering-0.0.3.dist-info/LICENSE
bldg_point_clustering-0.0.3.dist-info/METADATA
bldg_point_clustering-0.0.3.dist-info/WHEEL
bldg_point_clustering-0.0.3.dist-info/top_level.txt
bldg_point_clustering-0.0.3.dist-info/RECORD
